gemini_cli.py
gemcli-1.0.8.dist-info/licenses/LICENSE
gemcli-1.0.8.dist-info/METADATA
gemcli-1.0.8.dist-info/WHEEL
gemcli-1.0.8.dist-info/entry_points.txt
gemcli-1.0.8.dist-info/top_level.txt
gemcli-1.0.8.dist-info/RECORD
